mlmw/__init__.py
mlmw-0.1.0.dist-info/METADATA
mlmw-0.1.0.dist-info/WHEEL
mlmw-0.1.0.dist-info/RECORD
